gsheets_unify_adapter/__init__.py
gsheets_unify_adapter/gsheets_adapter.py
gsheets_unify_adapter/gsheets_grammar.lark
gsheets_unify_adapter/old_code.py
gsheets_unify_adapter/tests/test_gsheet_commands.py
gsheets_unify_adapter/tests/test_gsheets_adapter.py
unify/__init__.py
unify/__main__.py
unify/command_repl.py
unify/connectors.py
unify/data_utils.py
unify/db_wrapper.py
unify/email_helper.py
unify/file_adapter.py
unify/grammar.lark
unify/interpreter.py
unify/loading.py
unify/metabase_setup.py
unify/parsing_utils.py
unify/postgres_connector.py
unify/rest_connector.py
unify/rest_specs/__init__.py
unify/rest_specs/aws_costs_spec.yaml
unify/rest_specs/beta/gmail_spec.yaml
unify/rest_specs/beta/polygonio_spec.yaml
unify/rest_specs/beta/tokenterminal_spec.yaml
unify/rest_specs/coda_spec.yaml
unify/rest_specs/datadog_spec.yaml
unify/rest_specs/github_spec.yaml
unify/rest_specs/gsearch_spec.yaml
unify/rest_specs/gsheets_spec.yaml
unify/rest_specs/hubspot_spec.yaml
unify/rest_specs/jira_spec.yaml
unify/rest_specs/mocksvc_spec.yaml
unify/rest_specs/papertrail_spec.yaml
unify/rest_specs/postgres_spec.yaml
unify/rest_specs/publicapis_spec.yaml
unify/rest_specs/reddit_spec.yaml
unify/rest_specs/spec_doc.yaml
unify/rest_specs/stripe_spec.yaml
unify/rest_specs/tenders_spec.yaml
unify/rest_specs/tests/papertrail_systems_page1.json
unify/scheduler.py
unify/schemata.py
unify/search.py
unify/sqla_patch.py
unify/sqla_storage_manager.py
unify/storage_manager.py
unify/tests/__init__.py
unify/tests/conftest.py
unify/tests/connections.yaml
unify/tests/files/gh_repos.parquet
unify/tests/files/project_list.csv
unify/tests/test_adapter_config.py
unify/tests/test_commands.py
unify/tests/test_data_utils.py
unify/tests/test_imports.py
unify/tests/test_information_schema.py
unify/tests/test_pagers.py
unify/tests/test_parser.py
unify/tests/test_postgres_adapter.py
unify/tests/test_rest_adapter.py
unify/tests/test_rest_calls.py
unify/tests/test_scheduler.py
unify/tests/test_schemata.py
unifydb-0.2.3.dist-info/LICENSE.md
unifydb-0.2.3.dist-info/WHEEL
unifydb-0.2.3.dist-info/entry_points.txt
unifydb-0.2.3.dist-info/METADATA
unifydb-0.2.3.dist-info/RECORD
