Metadata-Version: 2.1
Name: unifydb
Version: 0.2.3
Summary: Your personal data warehouse
Home-page: https://github.com/scottpersinger/unify
License: Elastic-2.0
Author: Scott Persinger
Author-email: scottpersinger@gmail.com
Requires-Python: >=3.9,<4.0
Classifier: License :: Other/Proprietary License
Classifier: Programming Language :: Python :: 3
Classifier: Programming Language :: Python :: 3.9
Classifier: Programming Language :: Python :: 3.10
Classifier: Programming Language :: Python :: 3.11
Requires-Dist: altair (>=4.2.0,<5.0.0)
Requires-Dist: altair-viewer (>=0.4.0,<0.5.0)
Requires-Dist: clickhouse-driver (>=0.2.5,<0.3.0)
Requires-Dist: clickhouse-sqlalchemy (>=0.2.3,<0.3.0)
Requires-Dist: duckdb (>=0.6.1,<0.7.0)
Requires-Dist: duckdb-engine (>=0.6.8,<0.7.0)
Requires-Dist: google-api-python-client (>=2.70.0,<3.0.0)
Requires-Dist: google-auth-httplib2 (>=0.1.0,<0.2.0)
Requires-Dist: google-auth-oauthlib (>=0.8.0,<0.9.0)
Requires-Dist: ipykernel (>=6.19.4,<7.0.0)
Requires-Dist: ipynbname (>=2021.3.2,<2022.0.0)
Requires-Dist: jsonpath-ng (>=1.5.3,<2.0.0)
Requires-Dist: lark (>=1.1.5,<2.0.0)
Requires-Dist: nb2mail-unify (>=0.6,<0.7)
Requires-Dist: pandas (>=1.5.2,<2.0.0)
Requires-Dist: prompt-toolkit (>=3.0.36,<4.0.0)
Requires-Dist: pyaml (>=21.10.1,<22.0.0)
Requires-Dist: pyarrow (>=10.0.1,<11.0.0)
Requires-Dist: pytest (>=7.2.0,<8.0.0)
Requires-Dist: python-dotenv (>=0.21.0,<0.22.0)
Requires-Dist: pyzmq (>=24.0.1,<25.0.0)
Requires-Dist: redmail (>=0.4.2,<0.5.0)
Requires-Dist: requests (>=2.28.1,<3.0.0)
Requires-Dist: requests-aws4auth (>=1.1.2,<2.0.0)
Requires-Dist: signaling (>=1.0.0,<2.0.0)
Requires-Dist: sqlalchemy (>=1.4.45,<2.0.0)
Requires-Dist: sqlglot (>=10.3.2,<11.0.0)
Project-URL: Documentation, https://github.com/scottpersinger/unify/docs
Project-URL: Repository, https://github.com/scottpersinger/unify
